tospip/__init__.py
tospip-0.1.4.dist-info/WHEEL
tospip-0.1.4.dist-info/METADATA
tospip-0.1.4.dist-info/RECORD
