Metadata-Version: 2.1
Name: tospip
Version: 0.1.4
Summary: 
Author: Nick Bean
Author-email: nickbean2255@yahoo.com
Requires-Python: >=3.9,<4.0
Classifier: Programming Language :: Python :: 3
Classifier: Programming Language :: Python :: 3.9
Requires-Dist: Authlib (==0.15.3)
Requires-Dist: Flask (==1.1.2)
Requires-Dist: Jinja2 (==2.11.3)
Requires-Dist: MarkupSafe (==1.1.1)
Requires-Dist: Werkzeug (==1.0.1)
Requires-Dist: autopep8 (==1.5.7)
Requires-Dist: certifi (==2020.12.5)
Requires-Dist: cffi (==1.14.5)
Requires-Dist: chardet (==3.0.4)
Requires-Dist: click (==7.1.2)
Requires-Dist: colorama (==0.4.4)
Requires-Dist: cryptography (==3.4.6)
Requires-Dist: discord (==1.7.3)
Requires-Dist: discord.py (==1.7.3)
Requires-Dist: easygui (==0.98.2)
Requires-Dist: et-xmlfile (==1.1.0)
Requires-Dist: h11 (==0.12.0)
Requires-Dist: httpcore (==0.12.3)
Requires-Dist: httpx (==0.17.1)
Requires-Dist: idna (==2.10)
Requires-Dist: itsdangerous (==1.1.0)
Requires-Dist: lxml (==4.6.2)
Requires-Dist: numpy (==1.20.0)
Requires-Dist: oauthlib (==3.1.0)
Requires-Dist: openpyxl (==3.0.7)
Requires-Dist: pandas (==1.2.3)
Requires-Dist: parse (==1.19.0)
Requires-Dist: prompt-toolkit (==3.0.17)
Requires-Dist: psutil (==5.8.0)
Requires-Dist: pyOpenSSL (==20.0.1)
Requires-Dist: pycodestyle (==2.7.0)
Requires-Dist: pycparser (==2.20)
Requires-Dist: pynput (==1.7.3)
Requires-Dist: python-dateutil (==2.8.1)
Requires-Dist: pytz (==2021.1)
Requires-Dist: pywin32 (==301)
Requires-Dist: requests (==2.25.1)
Requires-Dist: requests-oauthlib (==1.3.0)
Requires-Dist: rfc3986 (==1.4.0)
Requires-Dist: selenium (==3.141.0)
Requires-Dist: six (==1.15.0)
Requires-Dist: sniffio (==1.2.0)
Requires-Dist: td-ameritrade-python-api (==0.3.5)
Requires-Dist: tda-api (==1.3.3)
Requires-Dist: urllib3 (==1.26.4)
Requires-Dist: wcwidth (==0.2.5)
Requires-Dist: websocket-client (==0.58.0)
Requires-Dist: websockets (==9.1)
Requires-Dist: xlwings (>=0.24.2,<0.25.0)
